deep_data_profiler/__init__.py
deep_data_profiler/exception.py
deep_data_profiler/read_write.py
deep_data_profiler/algorithms/__init__.py
deep_data_profiler/algorithms/homology.py
deep_data_profiler/algorithms/jaccard.py
deep_data_profiler/algorithms/spectral_analysis.py
deep_data_profiler/classes/__init__.py
deep_data_profiler/classes/channel_profiler.py
deep_data_profiler/classes/element_profiler.py
deep_data_profiler/classes/profile.py
deep_data_profiler/classes/spatial_profiler.py
deep_data_profiler/classes/svd_influential.py
deep_data_profiler/classes/torch_profiler.py
deep_data_profiler/optimization/__init__.py
deep_data_profiler/optimization/feature_helpers.py
deep_data_profiler/optimization/feature_objective.py
deep_data_profiler/optimization/input_feature.py
deep_data_profiler/optimization/optimization_sgd.py
deep_data_profiler/optimization/svd_utils.py
deep_data_profiler/utils/__init__.py
deep_data_profiler/utils/attribution_graphs.py
deep_data_profiler/utils/helpers.py
deep_data_profiler/utils/matrix_theory.py
deep_data_profiler/utils/torch_hook.py
deep_data_profiler-2.0.1.dist-info/LICENSE.rst
deep_data_profiler-2.0.1.dist-info/METADATA
deep_data_profiler-2.0.1.dist-info/WHEEL
deep_data_profiler-2.0.1.dist-info/top_level.txt
deep_data_profiler-2.0.1.dist-info/RECORD
