Metadata-Version: 2.1
Name: deep-data-profiler
Version: 2.0.1
Summary: The Deep Data Profilerlibrary provides tools for analyzing the internal decision structure of a trained deep neural network.
License: 3-Clause BSD license
License-File: LICENSE.rst
Requires-Dist: torch (>=1.10.2)
Requires-Dist: numpy (>=1.14.3)
Requires-Dist: networkx (>=2.5)
Requires-Dist: scipy
Requires-Dist: ripser (>=0.6.0)
Requires-Dist: powerlaw (>=1.4.6)
Requires-Dist: torchvision (>=0.11.3)
Requires-Dist: torch-lucent (>=0.1.8)
Provides-Extra: all
Requires-Dist: sphinx (>=1.8.2) ; extra == 'all'
Requires-Dist: nb2plots (>=0.6) ; extra == 'all'
Requires-Dist: sphinx-rtd-theme (>=0.4.2) ; extra == 'all'
Requires-Dist: sphinx-autodoc-typehints ; extra == 'all'
Requires-Dist: pytest (>=4.0) ; extra == 'all'
Requires-Dist: pillow (>=5.2.0) ; extra == 'all'
Requires-Dist: jupyter (>=1.0.0) ; extra == 'all'
Requires-Dist: opencv-python ; extra == 'all'
Requires-Dist: pytorchcv ; extra == 'all'
Requires-Dist: streamlit ; extra == 'all'
Requires-Dist: boto3 ; extra == 'all'
Provides-Extra: documentation
Requires-Dist: sphinx (>=1.8.2) ; extra == 'documentation'
Requires-Dist: nb2plots (>=0.6) ; extra == 'documentation'
Requires-Dist: sphinx-rtd-theme (>=0.4.2) ; extra == 'documentation'
Requires-Dist: sphinx-autodoc-typehints ; extra == 'documentation'
Provides-Extra: frontend
Requires-Dist: streamlit ; extra == 'frontend'
Requires-Dist: boto3 ; extra == 'frontend'
Provides-Extra: testing
Requires-Dist: pytest (>=4.0) ; extra == 'testing'
Provides-Extra: tutorials
Requires-Dist: pillow (>=5.2.0) ; extra == 'tutorials'
Requires-Dist: jupyter (>=1.0.0) ; extra == 'tutorials'
Requires-Dist: opencv-python ; extra == 'tutorials'
Requires-Dist: pytorchcv ; extra == 'tutorials'
